Metadata-Version: 2.1
Name: code-similarity
Version: 0.0.4
Summary: An out of box code and text similarity computation package
Home-page: https://github.com/RManLuo/code-similarity
Author: Raymond Luo
Author-email: luolinhao1998@gmail.com
License: UNKNOWN
Platform: UNKNOWN
